lizardwizard/__init__.py
lizardwizard/console.py
lizardwizard-0.2.0.dist-info/entry_points.txt
lizardwizard-0.2.0.dist-info/METADATA
lizardwizard-0.2.0.dist-info/WHEEL
lizardwizard-0.2.0.dist-info/RECORD
